pyCFOF/__init__.py
pyCFOF/_cfof.py
pyCFOF/tests/__init__.py
pyCFOF/tests/test_cfof.py
Concentration_Free_Outlier_Factor-0.3.1.dist-info/LICENSE
Concentration_Free_Outlier_Factor-0.3.1.dist-info/METADATA
Concentration_Free_Outlier_Factor-0.3.1.dist-info/WHEEL
Concentration_Free_Outlier_Factor-0.3.1.dist-info/top_level.txt
Concentration_Free_Outlier_Factor-0.3.1.dist-info/RECORD
