Metadata-Version: 2.1
Name: Concentration-Free-Outlier-Factor
Version: 0.3.1
Summary: Calculate the Concentration Free Outlier Factor score, based on Angiulli's work
Home-page: https://github.com/luk-f/pyCFOF
Author: Lucas Foulon
Author-email: lucas.foulon@gmail.com
License: UNKNOWN
Platform: UNKNOWN
Classifier: Programming Language :: Python :: 3
Classifier: License :: OSI Approved :: MIT License
Classifier: Operating System :: OS Independent
Requires-Python: >=3.6
